setup.py
brynq_sdk_newrelic/__init__.py
brynq_sdk_newrelic/newrelic_interface.py
brynq_sdk_newrelic.egg-info/PKG-INFO
brynq_sdk_newrelic.egg-info/SOURCES.txt
brynq_sdk_newrelic.egg-info/dependency_links.txt
brynq_sdk_newrelic.egg-info/not-zip-safe
brynq_sdk_newrelic.egg-info/requires.txt
brynq_sdk_newrelic.egg-info/top_level.txt