Metadata-Version: 1.0
Name: brynq-sdk-newrelic
Version: 1.0.3
Summary: Newrelic wrapper from BrynQ
Home-page: UNKNOWN
Author: BrynQ
Author-email: support@brynq.com
License: BrynQ License
Platform: UNKNOWN
